BeautifulDebug/__init__.py
BeautifulDebug/defines.py
BeautifulDebug/settings.py
BeautifulDebug/utils.py
BeautifulDebug-0.2.0.dist-info/DESCRIPTION.rst
BeautifulDebug-0.2.0.dist-info/METADATA
BeautifulDebug-0.2.0.dist-info/RECORD
BeautifulDebug-0.2.0.dist-info/WHEEL
BeautifulDebug-0.2.0.dist-info/metadata.json
BeautifulDebug-0.2.0.dist-info/top_level.txt
