Metadata-Version: 2.0
Name: BeautifulDebug
Version: 0.2.0
Summary: enjoy beautiful debug tools.
Home-page: https://github.com/xiaojieluo/BeautifulDebug
Author: Xiaojieluo
Author-email: xiaojieluoff@gmail.com
License: Apache License
Platform: UNKNOWN
Classifier: Intended Audience :: Developers
Classifier: License :: OSI Approved :: MIT License
Classifier: Operating System :: MacOS :: MacOS X
Classifier: Operating System :: Microsoft :: Windows
Classifier: Operating System :: POSIX
Classifier: Programming Language :: Python
Classifier: Programming Language :: Python :: 2
Classifier: Programming Language :: Python :: 3
Classifier: Topic :: Software Development :: Libraries :: Python Modules
Classifier: Programming Language :: Python :: Implementation :: PyPy
Classifier: Programming Language :: Python :: Implementation :: CPython
